pipall/__init__.py
pipall/pipall.py
pipall/pipallBackground.py
idev_pipall-1.0.0.dist-info/LICENSE
idev_pipall-1.0.0.dist-info/METADATA
idev_pipall-1.0.0.dist-info/WHEEL
idev_pipall-1.0.0.dist-info/entry_points.txt
idev_pipall-1.0.0.dist-info/top_level.txt
idev_pipall-1.0.0.dist-info/RECORD
