Metadata-Version: 2.1
Name: idev-pipall
Version: 1.0.0
Summary: A python script for executing pip commands across many or all packages.
Home-page: https://github.com/IrtsaDevelopment/pipall
Author: IrtsaDevelopment
Author-email: Irtsa <irtsa.development@gmail.com>
Project-URL: Homepage, https://github.com/IrtsaDevelopment/pipall
Project-URL: Bug Tracker, https://github.com/IrtsaDevelopment/pipall/issues
Classifier: Programming Language :: Python :: 3
Classifier: License :: OSI Approved :: MIT License
Classifier: Operating System :: OS Independent
Requires-Python: >=3.6
License-File: LICENSE
Requires-Dist: idev-pytermcolor
